nvtt/__init__.py
nvtt/compression.py
nvtt/context.py
nvtt/core.py
nvtt/enums/__init__.py
nvtt/enums/alpha_mode.py
nvtt/enums/channel.py
nvtt/enums/container.py
nvtt/enums/encode_flags.py
nvtt/enums/error.py
nvtt/enums/filters.py
nvtt/enums/format.py
nvtt/enums/normal_transform.py
nvtt/enums/pixel_type.py
nvtt/enums/quality.py
nvtt/enums/round_mode.py
nvtt/enums/severity.py
nvtt/enums/texture_type.py
nvtt/enums/tone_mapper.py
nvtt/enums/wrap_mode.py
nvtt/libs/FreeImage.dll
nvtt/libs/libnvtt.so.30205
nvtt/libs/nvtt30205.dll
nvtt/output.py
nvtt/surface.py
nvtt/utils/easy_dds.py
nvtt/utils/image_helper.py
pynvtt-0.0.2.dist-info/LICENSE
pynvtt-0.0.2.dist-info/METADATA
pynvtt-0.0.2.dist-info/WHEEL
pynvtt-0.0.2.dist-info/RECORD
