Metadata-Version: 2.3
Name: pynvtt
Version: 0.0.2
Summary: A simple Python wrapper for NVTT3 (NVIDIA Texture Tools 3)
License: CC0-1.0
Author: MrVicho13
Author-email: vicho0202@gmail.com
Requires-Python: >=3.10,<4.0
Classifier: License :: CC0 1.0 Universal (CC0 1.0) Public Domain Dedication
Classifier: Programming Language :: Python :: 3
Classifier: Programming Language :: Python :: 3.10
Classifier: Programming Language :: Python :: 3.11
Classifier: Programming Language :: Python :: 3.12
Classifier: Programming Language :: Python :: 3.13
Project-URL: Homepage, https://github.com/Hancapo/pynvtt
Project-URL: Repository, https://github.com/Hancapo/pyNVTT
